pg_logging/__init__.py
pg_logging/define.py
pg_logging/log_client.py
pg_logging/mock.py
pg_logging/tcp_handler.py
pg_logging-1.0.3.dist-info/METADATA
pg_logging-1.0.3.dist-info/WHEEL
pg_logging-1.0.3.dist-info/top_level.txt
pg_logging-1.0.3.dist-info/RECORD
