Metadata-Version: 2.1
Name: pg-logging
Version: 1.0.3
Summary: python game: logging
Author: baozilaji@gmail.com
Requires-Python: >=3.9
Requires-Dist: pg-environment >=0
